{
  "Name": "Bag",
  "Transform": {
    "posX": -11.4274111,
    "posY": 0.7749659,
    "posZ": 3.57388115,
    "rotX": 0.000004265533,
    "rotY": -4.93587663e-7,
    "rotZ": 0.00000431555873,
    "scaleX": 1,
    "scaleY": 1,
    "scaleZ": 1
  },
  "Nickname": "Bag of Stuff",
  "Description": "",
  "GMNotes": "",
  "ColorDiffuse": {
    "r": 0.7058823,
    "g": 0.366520882,
    "b": 0
  },
  "Locked": false,
  "Grid": true,
  "Snap": true,
  "IgnoreFoW": false,
  "Autoraise": true,
  "Sticky": true,
  "Tooltip": true,
  "GridProjection": false,
  "HideWhenFaceDown": false,
  "Hands": false,
  "MaterialIndex": -1,
  "MeshIndex": -1,
  "LuaScriptState": "",
  "GUID": "4dccf2",
  "$Children": [
    "block_triangle.3f4a4f",
    "block_rectangle.b60aa6"
  ]
}